{
  "name": "nevit_121",
  "description": "",
  "pieces": [
    {
      "piece": "large_triangle",
      "id": 0,
      "anchor": {
        "x": [
          2,
          -2
        ],
        "y": [
          40,
          -19
        ]
      },
      "orientation": 7,
      "flipped": false
    },
    {
      "piece": "large_triangle",
      "id": 1,
      "anchor": {
        "x": [
          2,
          -2
        ],
        "y": [
          40,
          -7
        ]
      },
      "orientation": 6,
      "flipped": false
    },
    {
      "piece": "medium_triangle",
      "id": 0,
      "anchor": {
        "x": [
          2,
          4
        ],
        "y": [
          40,
          -1
        ]
      },
      "orientation": 5,
      "flipped": false
    },
    {
      "piece": "small_triangle",
      "id": 0,
      "anchor": {
        "x": [
          -4,
          16
        ],
        "y": [
          34,
          -13
        ]
      },
      "orientation": 1,
      "flipped": false
    },
    {
      "piece": "small_triangle",
      "id": 1,
      "anchor": {
        "x": [
          14,
          -2
        ],
        "y": [
          28,
          -19
        ]
      },
      "orientation": 0,
      "flipped": false
    },
    {
      "piece": "square",
      "id": 0,
      "anchor": {
        "x": [
          2,
          10
        ],
        "y": [
          40,
          -7
        ]
      },
      "orientation": 6,
      "flipped": false
    },
    {
      "piece": "parallelogram",
      "id": 0,
      "anchor": {
        "x": [
          2,
          16
        ],
        "y": [
          40,
          -7
        ]
      },
      "orientation": 3,
      "flipped": false
    }
  ],
  "source": "https://commons.wikimedia.org/wiki/File:Tangram_121_Nevit.svg"
}
