{
  "name": "people_018",
  "description": "Tangram figure (Crouching)",
  "pieces": [
    {
      "piece": "large_triangle",
      "id": 0,
      "anchor": {
        "x": [
          7,
          -2
        ],
        "y": [
          -1,
          22
        ]
      },
      "orientation": 6,
      "flipped": false
    },
    {
      "piece": "large_triangle",
      "id": 1,
      "anchor": {
        "x": [
          1,
          10
        ],
        "y": [
          -7,
          10
        ]
      },
      "orientation": 2,
      "flipped": false
    },
    {
      "piece": "medium_triangle",
      "id": 0,
      "anchor": {
        "x": [
          7,
          -2
        ],
        "y": [
          -1,
          22
        ]
      },
      "orientation": 0,
      "flipped": false
    },
    {
      "piece": "small_triangle",
      "id": 0,
      "anchor": {
        "x": [
          13,
          -2
        ],
        "y": [
          5,
          22
        ]
      },
      "orientation": 1,
      "flipped": false
    },
    {
      "piece": "small_triangle",
      "id": 1,
      "anchor": {
        "x": [
          13,
          10
        ],
        "y": [
          5,
          22
        ]
      },
      "orientation": 5,
      "flipped": false
    },
    {
      "piece": "square",
      "id": 0,
      "anchor": {
        "x": [
          1,
          10
        ],
        "y": [
          -7,
          10
        ]
      },
      "orientation": 7,
      "flipped": false
    },
    {
      "piece": "parallelogram",
      "id": 0,
      "anchor": {
        "x": [
          7,
          -2
        ],
        "y": [
          11,
          10
        ]
      },
      "orientation": 6,
      "flipped": true
    }
  ],
  "source": "https://commons.wikimedia.org/wiki/File:Tangram_018_Nevit.svg"
}
