{
  "name": "nevit_039",
  "description": "",
  "pieces": [
    {
      "piece": "large_triangle",
      "id": 0,
      "anchor": {
        "x": [
          34,
          -18
        ],
        "y": [
          51,
          -24
        ]
      },
      "orientation": 6,
      "flipped": false
    },
    {
      "piece": "large_triangle",
      "id": 1,
      "anchor": {
        "x": [
          -20,
          24
        ],
        "y": [
          63,
          -24
        ]
      },
      "orientation": 5,
      "flipped": false
    },
    {
      "piece": "medium_triangle",
      "id": 0,
      "anchor": {
        "x": [
          12,
          18
        ],
        "y": [
          5,
          0
        ]
      },
      "orientation": 2,
      "flipped": false
    },
    {
      "piece": "small_triangle",
      "id": 0,
      "anchor": {
        "x": [
          34,
          -12
        ],
        "y": [
          9,
          18
        ]
      },
      "orientation": 6,
      "flipped": false
    },
    {
      "piece": "small_triangle",
      "id": 1,
      "anchor": {
        "x": [
          -23,
          18
        ],
        "y": [
          60,
          -24
        ]
      },
      "orientation": 0,
      "flipped": false
    },
    {
      "piece": "square",
      "id": 0,
      "anchor": {
        "x": [
          28,
          -6
        ],
        "y": [
          45,
          -24
        ]
      },
      "orientation": 7,
      "flipped": false
    },
    {
      "piece": "parallelogram",
      "id": 0,
      "anchor": {
        "x": [
          34,
          -24
        ],
        "y": [
          34,
          -24
        ]
      },
      "orientation": 1,
      "flipped": false
    }
  ],
  "source": "https://commons.wikimedia.org/wiki/File:Tangram_39_Nevit.svg"
}
