{
  "name": "nevit_061",
  "description": "",
  "pieces": [
    {
      "piece": "large_triangle",
      "id": 0,
      "anchor": {
        "x": [
          46,
          -24
        ],
        "y": [
          43,
          -12
        ]
      },
      "orientation": 1,
      "flipped": false
    },
    {
      "piece": "large_triangle",
      "id": 1,
      "anchor": {
        "x": [
          58,
          -24
        ],
        "y": [
          55,
          -12
        ]
      },
      "orientation": 5,
      "flipped": false
    },
    {
      "piece": "medium_triangle",
      "id": 0,
      "anchor": {
        "x": [
          40,
          0
        ],
        "y": [
          37,
          -24
        ]
      },
      "orientation": 2,
      "flipped": false
    },
    {
      "piece": "small_triangle",
      "id": 0,
      "anchor": {
        "x": [
          64,
          -24
        ],
        "y": [
          49,
          -12
        ]
      },
      "orientation": 1,
      "flipped": false
    },
    {
      "piece": "small_triangle",
      "id": 1,
      "anchor": {
        "x": [
          70,
          -24
        ],
        "y": [
          60,
          -24
        ]
      },
      "orientation": 1,
      "flipped": false
    },
    {
      "piece": "square",
      "id": 0,
      "anchor": {
        "x": [
          47,
          -12
        ],
        "y": [
          54,
          -24
        ]
      },
      "orientation": 7,
      "flipped": false
    },
    {
      "piece": "parallelogram",
      "id": 0,
      "anchor": {
        "x": [
          2,
          24
        ],
        "y": [
          -11,
          18
        ]
      },
      "orientation": 5,
      "flipped": true
    }
  ],
  "source": "https://commons.wikimedia.org/wiki/File:Tangram_61_Nevit.svg",
  "allow_disconnected": true
}
