{
  "name": "people_004",
  "description": "Tangram figure (Running)",
  "pieces": [
    {
      "piece": "large_triangle",
      "id": 0,
      "anchor": {
        "x": [
          24,
          1
        ],
        "y": [
          6,
          10
        ]
      },
      "orientation": 3,
      "flipped": false
    },
    {
      "piece": "large_triangle",
      "id": 1,
      "anchor": {
        "x": [
          24,
          1
        ],
        "y": [
          6,
          22
        ]
      },
      "orientation": 4,
      "flipped": false
    },
    {
      "piece": "medium_triangle",
      "id": 0,
      "anchor": {
        "x": [
          6,
          1
        ],
        "y": [
          -12,
          10
        ]
      },
      "orientation": 0,
      "flipped": false
    },
    {
      "piece": "small_triangle",
      "id": 0,
      "anchor": {
        "x": [
          24,
          1
        ],
        "y": [
          6,
          22
        ]
      },
      "orientation": 0,
      "flipped": false
    },
    {
      "piece": "small_triangle",
      "id": 1,
      "anchor": {
        "x": [
          24,
          1
        ],
        "y": [
          6,
          22
        ]
      },
      "orientation": 6,
      "flipped": false
    },
    {
      "piece": "square",
      "id": 0,
      "anchor": {
        "x": [
          12,
          1
        ],
        "y": [
          -6,
          10
        ]
      },
      "orientation": 7,
      "flipped": false
    },
    {
      "piece": "parallelogram",
      "id": 0,
      "anchor": {
        "x": [
          24,
          -5
        ],
        "y": [
          6,
          22
        ]
      },
      "orientation": 3,
      "flipped": false
    }
  ],
  "source": "https://commons.wikimedia.org/wiki/File:Tangram_004_Nevit.svg"
}
